pelper/__init__.py
pelper/misc.py
pelper/pipe.py
pelper-0.1.0.dist-info/DESCRIPTION.rst
pelper-0.1.0.dist-info/METADATA
pelper-0.1.0.dist-info/RECORD
pelper-0.1.0.dist-info/WHEEL
pelper-0.1.0.dist-info/metadata.json
pelper-0.1.0.dist-info/top_level.txt
