Metadata-Version: 2.0
Name: pelper
Version: 0.1.0
Summary: pelper - python helper functions
Home-page: https://github.com/sotte/pelper
Author: Stefan Otte
Author-email: stefan.otte@gmail.com
License: MIT
Download-URL: https://github.com/sotte/pelper
Keywords: development heper functional decorator contextmanager
Platform: UNKNOWN
